.gitignore
.gitmodules
.lint_exclusions
.pylintrc
LICENSE
MANIFEST.in
NOTICE
README.md
TODO
config_example.cfg
pylint-project.sh
pytest.ini
release-notes
setup.py
target_types_or_not.txt
bin/check_update_metric.py
bin/process_alerting.py
bin/run_graph_explorer.py
bin/update_metrics.py
graph_explorer/__init__.py
graph_explorer/app.py
graph_explorer/backend.py
graph_explorer/colors.py
graph_explorer/config.py
graph_explorer/convert.py
graph_explorer/dashboards.py
graph_explorer/log.py
graph_explorer/preferences.py
graph_explorer/preferences_color.py
graph_explorer/query.py
graph_explorer/simple_match.py
graph_explorer/suggested_queries.py
graph_explorer/target.py
graph_explorer/unitconv.py
graph_explorer/validation.py
graph_explorer.egg-info/PKG-INFO
graph_explorer.egg-info/SOURCES.txt
graph_explorer.egg-info/dependency_links.txt
graph_explorer.egg-info/requires.txt
graph_explorer.egg-info/top_level.txt
graph_explorer/alerting/__init__.py
graph_explorer/alerting/emailoutput.py
graph_explorer/assets/embed_example.html
graph_explorer/assets/css/bootstrap-responsive.css
graph_explorer/assets/css/bootstrap.css
graph_explorer/assets/css/tswidget.css
graph_explorer/assets/img/favicon.ico
graph_explorer/assets/img/glyphicons-halflings-white.png
graph_explorer/assets/img/glyphicons-halflings.png
graph_explorer/assets/js/bootbox.js
graph_explorer/assets/js/bootstrap.js
graph_explorer/assets/js/crc32.js
graph_explorer/assets/js/graph-explorer.js
graph_explorer/assets/js/jquery-1.7.2.js
graph_explorer/graphs/__init__.py
graph_explorer/graphs/plugins/__init__.py
graph_explorer/structured_metrics/README.md
graph_explorer/structured_metrics/__init__.py
graph_explorer/structured_metrics/plugins/__init__.py
graph_explorer/structured_metrics/plugins/carbon.py
graph_explorer/structured_metrics/plugins/catchall.py
graph_explorer/structured_metrics/plugins/catchall_diamond.py
graph_explorer/structured_metrics/plugins/catchall_statsd.py
graph_explorer/structured_metrics/plugins/collectd.py
graph_explorer/structured_metrics/plugins/cpu.py
graph_explorer/structured_metrics/plugins/diamond_openstack_swift.py
graph_explorer/structured_metrics/plugins/diamondcollectortime.py
