Metadata-Version: 1.0
Name: graph-explorer
Version: 2.0.2
Summary: A graphite dashboard powered by structured metrics
Home-page: http://vimeo.github.io/graph-explorer/
Author: Dieter Plaetinck
Author-email: dieter@plaetinck.be
License: apache2
Platform: UNKNOWN
